topsis_102203883/__init__.py
topsis_102203883/__main__.py
topsis_102203883-0.3.5.dist-info/METADATA
topsis_102203883-0.3.5.dist-info/WHEEL
topsis_102203883-0.3.5.dist-info/entry_points.txt
topsis_102203883-0.3.5.dist-info/top_level.txt
topsis_102203883-0.3.5.dist-info/RECORD
