Metadata-Version: 2.1
Name: topsis_102203883
Version: 0.3.5
Summary: a package to calculate topsis
